<?xml version = '1.0' encoding = 'UTF-8'?>
<Relation class="oracle.dbtools.crest.model.design.logical.Relation" name="Movimiento de inventario_Historial de inventario" directorySegmentName="seg_0" id="070BF6F5-9446-9C96-D5E2-69827E25D7DB">
<createdBy>santi</createdBy>
<createdTime>2024-06-16 22:35:45 UTC</createdTime>
<ownerDesignName>Logico_Rlacional_SENA_Proyeco</ownerDesignName>
<importedID>BE51D99B-8493-3491-5E54-069A5B7F728F</importedID>
<engineerTo>
<item key="F7C55B34-96D3-6518-B869-B9B5C302254D" value="true"/>
<item key="F0FAA670-0FAC-3E30-5555-73B0C777AE21" value="true"/>
<item key="0CCC3AA2-B753-B45D-4FB8-BE723AF9676F" value="true"/>
</engineerTo>
<sourcePk>5FDE92BA-D21D-10C0-B317-8F611A5409C4</sourcePk>
<identifying>false</identifying>
<optionalSource>true</optionalSource>
<optionalTarget>false</optionalTarget>
<sourceCardinality>1</sourceCardinality>
<sourceEntity>A64DDD36-9552-97F8-3D9A-554CC8A2F084</sourceEntity>
<targetCardinalityString>*</targetCardinalityString>
<targetEntity>41F6CD4E-7B92-AFCA-4DC3-8B8961FC5CCB</targetEntity>
<transferable>true</transferable>
<deleteRule>NO ACTION</deleteRule>
</Relation>