<?xml version = '1.0' encoding = 'UTF-8'?>
<Relation class="oracle.dbtools.crest.model.design.logical.Relation" name="Producto_Proveedor" directorySegmentName="seg_0" id="CAE53339-0E04-E3F6-519A-A70DF09ECAE1">
<createdBy>santi</createdBy>
<createdTime>2024-06-16 22:35:45 UTC</createdTime>
<ownerDesignName>Logico_Rlacional_SENA_Proyeco</ownerDesignName>
<importedID>E1110226-11EF-C415-C5BE-01776CE0264F</importedID>
<engineerTo>
<item key="F7C55B34-96D3-6518-B869-B9B5C302254D" value="true"/>
<item key="F0FAA670-0FAC-3E30-5555-73B0C777AE21" value="true"/>
<item key="0CCC3AA2-B753-B45D-4FB8-BE723AF9676F" value="true"/>
</engineerTo>
<identifying>false</identifying>
<optionalSource>true</optionalSource>
<optionalTarget>false</optionalTarget>
<sourceCardinality>*</sourceCardinality>
<sourceEntity>1FE06BE4-2524-6802-F11C-5105CA98DD7A</sourceEntity>
<targetCardinalityString>*</targetCardinalityString>
<targetEntity>26BD9793-557B-1CEE-D701-752E7681BDD9</targetEntity>
<transferable>true</transferable>
<deleteRule>NO ACTION</deleteRule>
</Relation>